{
    "categories": [
        "Building Management",
        "Emergency & Safety",
        "Financial Reports",
        "General Documents",
        "Insurance & Assessments",
        "Legal & Governance",
        "Maintenance & Installation",
        "Meeting Documents",
        "Resident Information",
        "Rules & Regulations",
        "Structural Reports",
        "Uncategorized"
    ],
    "file_categories": {
        "file-eBc9y5q9o8Cr75qWRafQ4kpC": "General Documents",
        "file-rFQr9JpPxb2ei8WxuZJpexfC": "Legal & Governance",
        "file-bc33bvpnxF8CG2uo8jYnbBCr": "Resident Information",
        "file-OJKAZ0a7n5PtiuY7a6qIT2Le": "Emergency & Safety",
        "file-k91y5JT9ltjofBdGjmpV63iP": "General Documents",
        "file-wr7pRSkHwRPVjwLF4B8r7J46": "Financial Reports",
        "file-vG2gdDWdy0hwmeveiofd9XJT": "Rules & Regulations",
        "file-y1UV9MgkHkgbSu8b3bgV9jCM": "General Documents",
        "file-O4JBNeOCblTCvL1jsc5XnZQC": "General Documents",
        "file-BwpXdzFVD9MG5StLuvD4mn5f": "General Documents",
        "file-ygTfZCKVqKcQlFlUbisMpN9S": "General Documents",
        "file-nn0OJWYgukyiLKZF0r79FdXO": "Legal & Governance",
        "file-039aFrkOb8u6dUM8sJ086dvm": "Maintenance & Installation",
        "file-2ji8aIm7NPU7SEJBHzj44DzI": "Building Management",
        "file-bhOzd3RfCK9SgmXLdiy3t8ws": "General Documents",
        "file-pdnv6KaDbFmfNHyAuILkQ5ad": "General Documents",
        "file-i9KHvYsnCimwLtDuanRqNhln": "Financial Reports",
        "file-scUZVUGBjUpWwSBIjxBQEKYQ": "General Documents",
        "file-vE6RbrF9GgKrVjSTI8y3ErSk": "Financial Reports",
        "file-qfPNT9livQttGKM4AskUkKFt": "Legal & Governance",
        "file-EjRSz8zk43teNN2zD4zOsM43": "Legal & Governance",
        "file-8vBTJkG3IAQy8cAcNcCsQPw7": "Legal & Governance",
        "file-BeBo3Tn3izAiDRkMpDW8TMAw": "General Documents",
        "file-OQhhVLS52zcrYOjNf1EvQX26": "General Documents",
        "file-qeBxj63u0SSbZhFbdtkWYctM": "Building Management",
        "file-7HzSe3ngcIRZwW2cCQE2T308": "General Documents",
        "file-b8DVRJ8ddPKzpK4bH8oLs2tC": "Resident Information",
        "file-r2Fxlcujgmiz3lMhsOScVdnf": "General Documents",
        "file-vGVAt6phoJ67CeFO4WXsKVqi": "Insurance & Assessments",
        "file-YCc9CGkDKCetwhLaoLpgsxwX": "Legal & Governance",
        "file-U8Pf1KNZAtX99fuenF3eN1yb": "Emergency & Safety",
        "file-0oyUHYYS49VhhWgJOAWfTX09": "General Documents",
        "file-z2qs8oOsHBmsPA9bxGYjfuZg": "General Documents",
        "file-aEZyci7WajT4LEydY0cAN8o4": "General Documents",
        "file-p7dfwBY77MLOTP637gdFQBK2": "Building Management",
        "file-03uyN7yJYEpKAbGgCUTiNcxz": "General Documents",
        "file-WaDAMPdooA2kOAOcXJ9k1g8z": "Legal & Governance",
        "file-SMdqbbKMOwgfvL06EwAhRasI": "Meeting Documents",
        "file-gCgFiPiRE909kpbEgz0koPBV": "General Documents",
        "file-ouBJM8KBWzmSUbGxYDQ2UBTG": "Legal & Governance",
        "file-En4EKcbbyE5sDbj7FdTdKyXr": "Financial Reports",
        "file-eBnqtwQnX3Ieo4AtrUwquhOd": "Building Management",
        "file-LgJK0nW4gXXcYkCahWxY7Q39": "Financial Reports",
        "file-mVBRophRS88ntVbZa2t5oPV4": "General Documents",
        "file-xIvffhNe9stn0PRnPUQCtUpJ": "Building Management",
        "file-iiXn2Xix2BUIrv0LwHs4snvy": "Maintenance & Installation",
        "file-AelwhTKBuYAmzcCTJGgySAzI": "Financial Reports",
        "file-YRJiDnZakMCHoAcbFPAiv7n9": "Emergency & Safety",
        "file-2ioOLuuSdFB3VAoP9WkYgXcv": "Financial Reports",
        "file-1Nm1QGSx7wGJBjgN9mhuEWPv": "Financial Reports",
        "file-whEycgAjLUTCAimRn2ESFDAY": "Meeting Documents",
        "file-AoSzB2ncZV93zQ5ebaQ4miVL": "General Documents",
        "file-BxK3kfdNoB20XKN70xCuTqNz": "Meeting Documents",
        "file-wJozllCU9JKLqTRFJ8Q8GIW5": "General Documents",
        "file-rSpFHxervAKLuYfsQBm6MKrc": "General Documents",
        "file-dSW2HiYZ5uEKHIbfVfffyxH7": "Rules & Regulations",
        "file-Y7m2hltxv8xphjh9hQrcvuWJ": "Financial Reports",
        "file-1vj1wWANwFVSKfvDjAn2cLRh": "General Documents",
        "file-evUAOaZ5TlV4KdgOtIiQXAlU": "General Documents",
        "file-idcgp9X9IcwwMdzPV5DYJJ1S": "General Documents",
        "file-nDDtH3BNWyi0b1MDtbe0ppFg": "Financial Reports",
        "file-O2f3on1joNRj7OKAaYwvwJS1": "Legal & Governance",
        "file-sDlH8Whux9M5egw2cZXgihho": "Legal & Governance",
        "file-AE6V96o2gHyPTDTQZ0XLUCMA": "General Documents",
        "file-h2JQRCjy0CPl0BGCIuq3MR42": "General Documents",
        "file-vgUL4QHV5KriaZhE3eB2pOEt": "General Documents",
        "file-R3GwO1sIBgWHeXqC7bNpRM0q": "Emergency & Safety",
        "file-rPvzZKurWKUvPNEEaGERQJmL": "Legal & Governance",
        "file-GSBtByFDkfmgz4ZBZojjyEhg": "General Documents",
        "file-yuVrJ44fQFsi2ha7aRj8LDbx": "Meeting Documents",
        "file-jmYXqsdBVdgMWJUupLSMGpfo": "General Documents",
        "file-WkKGbdbu22FbKvglxpqwOJ4B": "Financial Reports",
        "file-08z32JxvfPtbTpaPR52wsz8j": "Building Management",
        "file-x9Xa2QslEt5qPudejOQSTMTX": "Legal & Governance",
        "file-WO8aEhf6PBR1lbgaISGtcqXb": "Meeting Documents",
        "file-dGLS0GHxXoHAYVtbUmPhSuYb": "General Documents",
        "file-FRZ14F8931jQJh9T77Ub1u": "Financial Reports",
        "file-zsoWLwtGQPLLPYAXRe8wrhZE": "Building Management",
        "file-Tk46hASMeRxACPgVHaYgpYmI": "Structural Reports",
        "file-EX5LTL86QioNyV7j6IOwgq1S": "General Documents"
    }
}